napari_bfio/__init__.py
napari_bfio/_reader.py
napari_bfio/_writer.py
napari_bfio/napari.yaml
napari_bfio/_tests/__init__.py
napari_bfio/_tests/test_reader.py
napari_bfio/_tests/test_writer.py
napari_bfio-0.0.4.dist-info/LICENSE
napari_bfio-0.0.4.dist-info/METADATA
napari_bfio-0.0.4.dist-info/WHEEL
napari_bfio-0.0.4.dist-info/entry_points.txt
napari_bfio-0.0.4.dist-info/top_level.txt
napari_bfio-0.0.4.dist-info/RECORD
