Metadata-Version: 2.1
Name: napari-bfio
Version: 0.0.4
Summary: A plugin to read and write images using bfio within napari
Home-page: https://github.com/PolusAI/napari-bfio
Author: Sameeul B Samee
Author-email: sameeul.samee@nih.gov
License: MIT
Project-URL: Bug Tracker, https://github.com/PolusAI/napari-bfio/issues
Project-URL: Documentation, https://github.com/PolusAI/napari-bfio#README.md
Project-URL: Source Code, https://github.com/PolusAI/napari-bfio
Project-URL: User Support, https://github.com/PolusAI/napari-bfio/issues
Classifier: Development Status :: 2 - Pre-Alpha
Classifier: Framework :: napari
Classifier: Intended Audience :: Developers
Classifier: License :: OSI Approved :: MIT License
Classifier: Operating System :: OS Independent
Classifier: Programming Language :: Python
Classifier: Programming Language :: Python :: 3
Classifier: Programming Language :: Python :: 3 :: Only
Classifier: Programming Language :: Python :: 3.8
Classifier: Programming Language :: Python :: 3.9
Classifier: Programming Language :: Python :: 3.10
Classifier: Topic :: Scientific/Engineering :: Image Processing
Requires-Python: >=3.8
License-File: LICENSE
Requires-Dist: numpy
Requires-Dist: bfio >=2.3.1
Provides-Extra: testing
Requires-Dist: tox ; extra == 'testing'
Requires-Dist: pytest ; extra == 'testing'
Requires-Dist: pytest-cov ; extra == 'testing'
